airt/__init__.py
airt/_constant.py
airt/_helper.py
airt/_logger.py
airt/_modidx.py
airt/_sanitizer.py
airt/client.py
airt/_cli/__init__.py
airt/_cli/api_key.py
airt/_cli/cli.py
airt/_cli/db.py
airt/_cli/ds.py
airt/_cli/helper.py
airt/_cli/model.py
airt/_cli/pred.py
airt/_cli/token.py
airt/_cli/user.py
airt/_cli/version.py
airt/_components/__init__.py
airt/_components/api_key.py
airt/_components/client.py
airt/_components/datablob.py
airt/_components/datasource.py
airt/_components/model.py
airt/_components/prediction.py
airt/_components/progress_status.py
airt/_components/user.py
airt/_docstring/__init__.py
airt/_docstring/helpers.py
airt/_testing/__init__.py
airt/_testing/activate_by_import.py
airt_client-2023.3.0.dist-info/LICENSE
airt_client-2023.3.0.dist-info/METADATA
airt_client-2023.3.0.dist-info/WHEEL
airt_client-2023.3.0.dist-info/entry_points.txt
airt_client-2023.3.0.dist-info/top_level.txt
airt_client-2023.3.0.dist-info/RECORD
