Metadata-Version: 2.1
Name: airt-client
Version: 2023.3.0
Summary: Python client for airt-service
Home-page: https://github.com/airtai/airt-client
Author: airt.ai
Author-email: info@airt.ai
License: Creative Commons License
Keywords: nbdev jupyter notebook python airt keras tensorflow ML AI
Platform: UNKNOWN
Classifier: Development Status :: 4 - Beta
Classifier: Intended Audience :: Developers
Classifier: Natural Language :: English
Classifier: Programming Language :: Python :: 3.7
Classifier: Programming Language :: Python :: 3.8
Classifier: Programming Language :: Python :: 3.9
Classifier: Programming Language :: Python :: 3.10
Classifier: License :: Free for non-commercial use
Requires-Python: >=3.7
License-File: LICENSE
Requires-Dist: fastcore (>=1.3.26)
Requires-Dist: humanize (>=3.12.0)
Requires-Dist: pandas (>=1.3.0)
Requires-Dist: qrcode[pil] (>=7.3.1)
Requires-Dist: requests (>=2.23.0)
Requires-Dist: tabulate (>=0.8.9)
Requires-Dist: tqdm (>=4.62.0)
Requires-Dist: typer (>=0.3.2)
Provides-Extra: dev
Requires-Dist: awscli (==1.27.81) ; extra == 'dev'
Requires-Dist: azure-identity (==1.12.0) ; extra == 'dev'
Requires-Dist: azure-mgmt-storage (==21.0.0) ; extra == 'dev'
Requires-Dist: bandit (==1.7.4) ; extra == 'dev'
Requires-Dist: black (==23.1.0) ; extra == 'dev'
Requires-Dist: boto3 (==1.26.81) ; extra == 'dev'
Requires-Dist: detect-secrets (==1.4.0) ; extra == 'dev'
Requires-Dist: mypy (==1.0.1) ; extra == 'dev'
Requires-Dist: mysqlclient (==2.1.1) ; extra == 'dev'
Requires-Dist: nbdev-mkdocs (==0.1.0) ; extra == 'dev'
Requires-Dist: openai (==0.25.0) ; extra == 'dev'
Requires-Dist: pre-commit (==3.1.1) ; extra == 'dev'
Requires-Dist: pyarrow (==11.0.0) ; extra == 'dev'
Requires-Dist: pytest (==7.2.1) ; extra == 'dev'
Requires-Dist: semgrep (==1.13.0) ; extra == 'dev'
Requires-Dist: sqlmodel (==0.0.8) ; extra == 'dev'
Requires-Dist: types-requests (==2.28.11.15) ; extra == 'dev'
Requires-Dist: types-tabulate (==0.9.0.1) ; extra == 'dev'
